README
hflags.py
setup.py
hflags.egg-info/PKG-INFO
hflags.egg-info/SOURCES.txt
hflags.egg-info/dependency_links.txt
hflags.egg-info/requires.txt
hflags.egg-info/top_level.txt