Metadata-Version: 1.0
Name: hflags
Version: 1.0
Summary: Extended Google Commandline Flags Module
Home-page: http://github.com/termie/hflags
Author: Andy Smith
Author-email: hflags_py@anarkystic.com
License: Apache 2.0
Platform: UNKNOWN
